pynvml/__init__.py
pynvml/_version.py
pynvml/nvml.py
pynvml/smi.py
pynvml_utils/__init__.py
pynvml_utils/smi.py
pynvml-11.5.2.dist-info/LICENSE.txt
pynvml-11.5.2.dist-info/METADATA
pynvml-11.5.2.dist-info/WHEEL
pynvml-11.5.2.dist-info/top_level.txt
pynvml-11.5.2.dist-info/RECORD
