Metadata-Version: 2.1
Name: pynvml
Version: 11.5.2
Summary: Python utilities for the NVIDIA Management Library
Home-page: http://www.nvidia.com/
Author: NVIDIA Corporation
Author-email: rzamora@nvidia.com
License: BSD
Classifier: Development Status :: 7 - Inactive
Classifier: Intended Audience :: Developers
Classifier: Intended Audience :: System Administrators
Classifier: License :: OSI Approved :: BSD License
Classifier: Operating System :: Microsoft :: Windows
Classifier: Operating System :: POSIX :: Linux
Classifier: Programming Language :: Python
Classifier: Topic :: Software Development :: Libraries :: Python Modules
Classifier: Topic :: System :: Hardware
Classifier: Topic :: System :: Systems Administration
Requires-Python: >=3.6
License-File: LICENSE.txt
